obj_tables/__init__.py
obj_tables/__main__.py
obj_tables/_version.py
obj_tables/abstract.py
obj_tables/core.py
obj_tables/grammar.py
obj_tables/io.py
obj_tables/migrate.py
obj_tables/utils.py
obj_tables/web_service.py
obj_tables/bio/__init__.py
obj_tables/bio/seq.py
obj_tables/chem/__init__.py
obj_tables/chem/core.py
obj_tables/chem/reaction_equation.lark
obj_tables/math/__init__.py
obj_tables/math/expression.py
obj_tables/math/numeric.py
obj_tables/math/symbolic.py
obj_tables/sci/__init__.py
obj_tables/sci/onto.py
obj_tables/sci/refs.py
obj_tables/sci/uncertainty.py
obj_tables/sci/units.py
obj_tables/web/index.html
obj_tables-1.0.14.dist-info/LICENSE
obj_tables-1.0.14.dist-info/METADATA
obj_tables-1.0.14.dist-info/WHEEL
obj_tables-1.0.14.dist-info/entry_points.txt
obj_tables-1.0.14.dist-info/top_level.txt
obj_tables-1.0.14.dist-info/RECORD
