Metadata-Version: 2.1
Name: obj-tables
Version: 1.0.14
Summary: Tools for creating and reusing high-quality spreadsheets
Home-page: https://github.com/KarrLab/obj_tables
Author: ObjTables developers
Author-email: info@objtables.org
License: MIT
Download-URL: https://github.com/KarrLab/obj_tables
Keywords: object model,schema,workbook,XLSX,Excel,validation
Platform: UNKNOWN
Classifier: Development Status :: 4 - Beta
Classifier: Intended Audience :: Developers
Classifier: Intended Audience :: Science/Research
Classifier: Natural Language :: English
Classifier: Topic :: Database
Classifier: Topic :: Database :: Database Engines/Servers
Classifier: Topic :: Office/Business :: Financial :: Spreadsheet
Classifier: Topic :: Scientific/Engineering
Classifier: Topic :: Scientific/Engineering :: Bio-Informatics
Classifier: Topic :: Software Development :: Object Brokering
Classifier: Topic :: Software Development :: Libraries
Classifier: Topic :: Software Development :: Libraries :: Python Modules
Classifier: License :: OSI Approved :: MIT License
Classifier: Operating System :: OS Independent
Classifier: Programming Language :: Python :: 3
Classifier: Programming Language :: Python :: 3.6
Classifier: Programming Language :: Python :: 3.7
Requires-Dist: cement
Requires-Dist: inflect
Requires-Dist: natsort
Requires-Dist: networkx
Requires-Dist: python-dateutil
Requires-Dist: pyyaml (>=5.1)
Requires-Dist: setuptools
Requires-Dist: stringcase
Requires-Dist: validate-email
Requires-Dist: wc-utils (>=0.0.22)
Provides-Extra: all
Requires-Dist: abduct ; extra == 'all'
Requires-Dist: attrdict ; extra == 'all'
Requires-Dist: bcforms ; extra == 'all'
Requires-Dist: biopython (>=1.75) ; extra == 'all'
Requires-Dist: bpforms ; extra == 'all'
Requires-Dist: capturer ; extra == 'all'
Requires-Dist: configobj ; extra == 'all'
Requires-Dist: flask ; extra == 'all'
Requires-Dist: flask-cors ; extra == 'all'
Requires-Dist: flask-restplus ; extra == 'all'
Requires-Dist: gitpython ; extra == 'all'
Requires-Dist: graphviz (>=0.13) ; extra == 'all'
Requires-Dist: jupyter-client ; extra == 'all'
Requires-Dist: lark-parser ; extra == 'all'
Requires-Dist: matplotlib ; extra == 'all'
Requires-Dist: mock ; extra == 'all'
Requires-Dist: nbconvert ; extra == 'all'
Requires-Dist: nbformat ; extra == 'all'
Requires-Dist: notebook ; extra == 'all'
Requires-Dist: numpy ; extra == 'all'
Requires-Dist: objsize ; extra == 'all'
Requires-Dist: openbabel (<3) ; extra == 'all'
Requires-Dist: openpyxl (<=3.0.1) ; extra == 'all'
Requires-Dist: pandas ; extra == 'all'
Requires-Dist: pint (>=0.10) ; extra == 'all'
Requires-Dist: pronto (>=1) ; extra == 'all'
Requires-Dist: psutil ; extra == 'all'
Requires-Dist: pygithub ; extra == 'all'
Requires-Dist: pytest ; extra == 'all'
Requires-Dist: python-libsbml (>=5.16.0) ; extra == 'all'
Requires-Dist: scipy ; extra == 'all'
Requires-Dist: sphinx (>=1.8) ; extra == 'all'
Requires-Dist: sphinx-fontawesome ; extra == 'all'
Requires-Dist: sphinx-rtd-theme (>=0.4.2) ; extra == 'all'
Requires-Dist: sphinxcontrib-addmetahtml (>=0.1.1) ; extra == 'all'
Requires-Dist: sphinxcontrib-bibtex ; extra == 'all'
Requires-Dist: sphinxcontrib-googleanalytics (>=0.1.1) ; extra == 'all'
Requires-Dist: sphinxcontrib-spelling ; extra == 'all'
Requires-Dist: sphinxprettysearchresults ; extra == 'all'
Requires-Dist: sympy ; extra == 'all'
Requires-Dist: uncertainties ; extra == 'all'
Requires-Dist: wc-onto (>=0.0.2) ; extra == 'all'
Requires-Dist: wc-utils[git] ; extra == 'all'
Requires-Dist: werkzeug (<1) ; extra == 'all'
Provides-Extra: bio
Requires-Dist: biopython (>=1.75) ; extra == 'bio'
Provides-Extra: chem
Requires-Dist: bcforms ; extra == 'chem'
Requires-Dist: bpforms ; extra == 'chem'
Requires-Dist: openbabel (<3) ; extra == 'chem'
Provides-Extra: docs
Requires-Dist: sphinx (>=1.8) ; extra == 'docs'
Requires-Dist: sphinx-fontawesome ; extra == 'docs'
Requires-Dist: sphinx-rtd-theme (>=0.4.2) ; extra == 'docs'
Requires-Dist: sphinxcontrib-addmetahtml (>=0.1.1) ; extra == 'docs'
Requires-Dist: sphinxcontrib-bibtex ; extra == 'docs'
Requires-Dist: sphinxcontrib-googleanalytics (>=0.1.1) ; extra == 'docs'
Requires-Dist: sphinxcontrib-spelling ; extra == 'docs'
Requires-Dist: sphinxprettysearchresults ; extra == 'docs'
Provides-Extra: grammar
Requires-Dist: lark-parser ; extra == 'grammar'
Provides-Extra: math
Requires-Dist: numpy ; extra == 'math'
Requires-Dist: pandas ; extra == 'math'
Requires-Dist: sympy ; extra == 'math'
Provides-Extra: revisioning
Requires-Dist: gitpython ; extra == 'revisioning'
Requires-Dist: wc-utils[git] ; extra == 'revisioning'
Provides-Extra: sci
Requires-Dist: pint (>=0.10) ; extra == 'sci'
Requires-Dist: pronto (>=1) ; extra == 'sci'
Requires-Dist: uncertainties ; extra == 'sci'
Provides-Extra: tests
Requires-Dist: abduct ; extra == 'tests'
Requires-Dist: attrdict ; extra == 'tests'
Requires-Dist: capturer ; extra == 'tests'
Requires-Dist: configobj ; extra == 'tests'
Requires-Dist: jupyter-client ; extra == 'tests'
Requires-Dist: matplotlib ; extra == 'tests'
Requires-Dist: mock ; extra == 'tests'
Requires-Dist: nbconvert ; extra == 'tests'
Requires-Dist: nbformat ; extra == 'tests'
Requires-Dist: notebook ; extra == 'tests'
Requires-Dist: objsize ; extra == 'tests'
Requires-Dist: openpyxl (<=3.0.1) ; extra == 'tests'
Requires-Dist: psutil ; extra == 'tests'
Requires-Dist: pygithub ; extra == 'tests'
Requires-Dist: pytest ; extra == 'tests'
Requires-Dist: python-libsbml (>=5.16.0) ; extra == 'tests'
Requires-Dist: scipy ; extra == 'tests'
Requires-Dist: wc-onto (>=0.0.2) ; extra == 'tests'
Provides-Extra: viz
Requires-Dist: graphviz (>=0.13) ; extra == 'viz'
Provides-Extra: web
Requires-Dist: flask ; extra == 'web'
Requires-Dist: flask-cors ; extra == 'web'
Requires-Dist: flask-restplus ; extra == 'web'
Requires-Dist: werkzeug (<1) ; extra == 'web'
